calypsso/__about__.py
calypsso/__init__.py
calypsso/mail.py
calypsso/py.typed
calypsso/web.py
calypsso/mail_templates/account-activation.html
calypsso/mail_templates/account-exist.html
calypsso/mail_templates/account-invitation-required.html
calypsso/mail_templates/account-invitation.html
calypsso/mail_templates/account-merged.html
calypsso/mail_templates/mail-migration-already-exist.html
calypsso/mail_templates/mail-migration-confirmation.html
calypsso/mail_templates/mypayment-device-activation.html
calypsso/mail_templates/mypayment-structure-transfer.html
calypsso/mail_templates/mypayment-tos-signed.html
calypsso/mail_templates/reset-password-account-does-not-exist.html
calypsso/mail_templates/reset-password.html
calypsso/mail_templates/images/logo.png
calypsso/public/404.html
calypsso/public/app_store_button.png
calypsso/public/favicon.ico
calypsso/public/logo.png
calypsso/public/play_store_button.png
calypsso/public/404/index.html
calypsso/public/_next/static/chunks/01c863e2-5eebf491dce85361.js
calypsso/public/_next/static/chunks/06a6f6f4-d6dbac91fff5079c.js
calypsso/public/_next/static/chunks/149-4b5230e42c8571ca.js
calypsso/public/_next/static/chunks/295-dff723b069c9faac.js
calypsso/public/_next/static/chunks/2e71310a-3a8d0928659f05fb.js
calypsso/public/_next/static/chunks/305-637901f5fab39d11.js
calypsso/public/_next/static/chunks/340-8588d89da68ff0f2.js
calypsso/public/_next/static/chunks/364-94a796b7a344dc2d.js
calypsso/public/_next/static/chunks/390-b2a2e4c87e768dcb.js
calypsso/public/_next/static/chunks/408ca96d-e0239c9f7ba39b5f.js
calypsso/public/_next/static/chunks/415-673204164dc8427b.js
calypsso/public/_next/static/chunks/517-323c467faaf6cb31.js
calypsso/public/_next/static/chunks/519-e59a5fc2d603f46a.js
calypsso/public/_next/static/chunks/618f8807-89d2faab28039d86.js
calypsso/public/_next/static/chunks/741-1f247cc53cb06418.js
calypsso/public/_next/static/chunks/88cb64d0-1fb23ed929dad72b.js
calypsso/public/_next/static/chunks/904-13eaac38f6751a44.js
calypsso-2.6.1.dist-info/METADATA
calypsso-2.6.1.dist-info/WHEEL
calypsso-2.6.1.dist-info/licenses/LICENSE
calypsso-2.6.1.dist-info/RECORD
