Metadata-Version: 2.4
Name: CalypSSO
Version: 2.6.1
Summary: A small and static Next.js frontend for Hyperion
Project-URL: Source, https://github.com/aeecleclair/CalypSSO
Author: AEECL ECLAIR
License-Expression: MIT
License-File: LICENSE
Classifier: Programming Language :: Python
Classifier: Programming Language :: Python :: 3.8
Classifier: Programming Language :: Python :: 3.9
Classifier: Programming Language :: Python :: 3.10
Classifier: Programming Language :: Python :: 3.11
Classifier: Programming Language :: Python :: 3.12
Requires-Python: >=3.8
Requires-Dist: jinja2>=3.1
Requires-Dist: starlette>=0.37
